<?xml version="1.0" encoding="utf-8" ?>
<dwsync>
<file name="cookie.php" server="steel15.club/public_html/" local="131792362351724168" remote="131761440000000000" Dst="0" />
<file name="dev.php" server="steel15.club/public_html/" local="131792362379328953" remote="131761440000000000" Dst="0" />
<file name="dev_detail.php" server="steel15.club/public_html/" local="131792362386579631" remote="131761440000000000" Dst="0" />
<file name="dev_finish2.php" server="steel15.club/public_html/" local="131792362392532052" remote="131761440000000000" Dst="0" />
<file name="dev_insert.php" server="steel15.club/public_html/" local="131792362398476159" remote="131761440000000000" Dst="0" />
<file name="dev_finish.php" server="steel15.club/public_html/" local="131792362389483123" remote="131761440000000000" Dst="0" />
<file name="dev_insert2.php" server="steel15.club/public_html/" local="131792362400889728" remote="131761440000000000" Dst="0" />
<file name="dev_post.php" server="steel15.club/public_html/" local="131792362404409267" remote="131761440000000000" Dst="0" />
<file name="dev_pre.php" server="steel15.club/public_html/" local="131792362407831495" remote="131761440000000000" Dst="0" />
<file name="dev_update.php" server="steel15.club/public_html/" local="131792362410314513" remote="131761440000000000" Dst="0" />
<file name="download-ics.php" server="steel15.club/public_html/" local="131792362410633667" remote="131761440000000000" Dst="0" />
<file name="email.php" server="steel15.club/public_html/" local="131792362413117054" remote="131761440000000000" Dst="0" />
<file name="email.class.php" server="steel15.club/public_html/" local="131792362418005866" remote="131761440000000000" Dst="0" />
<file name="ics.php" server="steel15.club/public_html/" local="131792362544724574" remote="131761440000000000" Dst="0" />
<file name="index.php" server="steel15.club/public_html/" local="131792362445812858" remote="131792357400000000" Dst="0" />
<file name="logout.php" server="steel15.club/public_html/" local="131792361918007860" remote="131761440000000000" Dst="0" />
<file name="main.js" server="steel15.club/public_html/" local="131792361918057735" remote="131761440000000000" Dst="0" />
<file name="pan.php" server="steel15.club/public_html/" local="131792362561047213" remote="131761440000000000" Dst="0" />
<file name="post1.php" server="steel15.club/public_html/" local="131792361920441361" remote="131761440000000000" Dst="0" />
<file name="postemail.php" server="steel15.club/public_html/" local="131792361920431397" remote="131761440000000000" Dst="0" />
<file name="unload.php" server="steel15.club/public_html/" local="131792361923204091" remote="131761440000000000" Dst="0" />
<file name="upload_file.php" server="steel15.club/public_html/" local="131792361922755184" remote="131761440000000000" Dst="0" />
</dwsync>